adafruit_simplemath.py
adafruit_circuitpython_simplemath-2.0.17.dist-info/licenses/LICENSE
adafruit_circuitpython_simplemath-2.0.17.dist-info/METADATA
adafruit_circuitpython_simplemath-2.0.17.dist-info/WHEEL
adafruit_circuitpython_simplemath-2.0.17.dist-info/top_level.txt
adafruit_circuitpython_simplemath-2.0.17.dist-info/RECORD
